image_tools/__init__.py
image_tools/sizes.py
image_tools-1.0.0.dist-info/LICENSE.txt
image_tools-1.0.0.dist-info/METADATA
image_tools-1.0.0.dist-info/WHEEL
image_tools-1.0.0.dist-info/top_level.txt
image_tools-1.0.0.dist-info/RECORD
